commitlyCLI/__init__.py
commitlyCLI/__main__.py
commitlyCLI/cli.py
commitlyCLI/logo.py
Commitly_cli-1.1.5.dist-info/LICENSE
Commitly_cli-1.1.5.dist-info/METADATA
Commitly_cli-1.1.5.dist-info/WHEEL
Commitly_cli-1.1.5.dist-info/entry_points.txt
Commitly_cli-1.1.5.dist-info/top_level.txt
Commitly_cli-1.1.5.dist-info/RECORD
