Metadata-Version: 2.1
Name: Commitly-cli
Version: 1.1.5
Summary: CLI tool to generate structured Git commit messages using AI.
Home-page: https://github.com/Tostenn/Commitly-CLI
Author: Kouya Tosten
Author-email: kouyatosten@gmail.com
Classifier: Programming Language :: Python :: 3
Classifier: License :: OSI Approved :: MIT License
Classifier: Operating System :: OS Independent
Classifier: Intended Audience :: Developers
Classifier: Topic :: Software Development :: Version Control
Requires-Python: >=3.7
License-File: LICENSE
Requires-Dist: rich==13.7.1
Requires-Dist: commitly>=3.1.3
